hkw/data_.py
hkw/hkw.py
hkw/hkw1.py
hkw/rdata_/(2019년 14차 한국복지패널조사) 조사설계서-가구용(beta1).xlsx
hkw/rdata_/14차 머지데이터_변수명_200422.xlsx
hkw/rdata_/6110000_서울특별시_07_24_04_P_일반음식점.csv
hkw/rdata_/exam.csv
hkw/rdata_/exam_na.csv
hkw/rdata_/koweps_hpwc14_2019_beta1.sav
hkw/rdata_/leisure.csv
hkw/rdata_/midwest1.csv
hkw/rdata_/mpg1.csv
hkw/rdata_/mpg1_out.csv
hkw/rdata_/mpg2.csv
hkw/rdata_/mpg3.csv
hkw/rdata_/mpg4.csv
hkw/rdata_/mpg5.csv
hkw/rdata_/mpg6.csv
hkw/rdata_/mtcars.csv
hkw/rdata_/ozone.csv
hkw/rdata_/student.csv
hkw/rdata_/student.sav
hkw/rdata_/student1.csv
hkw/rdata_/student1.txt
hkw/rdata_/student1_xl.xlsx
hkw/rdata_/student2.csv
hkw/rdata_/student2.txt
hkw/rdata_/student3.txt
hkw/rdata_/student_xl.xlsx
hkw/rdata_/subway_2005.csv
hkw/rdata_/서울대기오염_2019.xlsx
hkw/rdata_/한국행정연구원_사회통합실태조사_데이터_2019.sav
hkw/rdata_/한국행정연구원_사회통합실태조사_설문지_2019.hwp
hkw1/hkw2.py
hkw-1.2.4.dist-info/METADATA
hkw-1.2.4.dist-info/WHEEL
hkw-1.2.4.dist-info/top_level.txt
hkw-1.2.4.dist-info/RECORD
