Metadata-Version: 2.1
Name: hkw
Version: 1.2.4
Summary: hkwarray.
Author: hkw
Author-email: kkhwer@gmail.com
License: UNKNOWN
Platform: UNKNOWN
